altcompare/__init__.py
altcompare-0.0.2.dist-info/METADATA
altcompare-0.0.2.dist-info/RECORD
altcompare-0.0.2.dist-info/WHEEL
altcompare-0.0.2.dist-info/top_level.txt
